salad/__init__.py
salad/optim.py
salad/structural.py
salad/datasets/__init__.py
salad/datasets/utils.py
salad/datasets/da/__init__.py
salad/datasets/da/base.py
salad/datasets/da/digits.py
salad/datasets/da/toy.py
salad/datasets/digits/__init__.py
salad/datasets/digits/base.py
salad/datasets/digits/mnist.py
salad/datasets/digits/openset.py
salad/datasets/digits/svhn.py
salad/datasets/digits/synth.py
salad/datasets/digits/usps.py
salad/datasets/transforms/__init__.py
salad/datasets/transforms/digits.py
salad/datasets/transforms/ensembling.py
salad/datasets/transforms/noise.py
salad/datasets/transforms/noisy.py
salad/datasets/visda/__init__.py
salad/datasets/visda/detection.py
salad/datasets/visda/openset.py
salad/datasets/visda/utils.py
salad/datasets/visda/visda.py
salad/layers/__init__.py
salad/layers/association.py
salad/layers/base.py
salad/layers/coral.py
salad/layers/da.py
salad/layers/funcs.py
salad/layers/mat.py
salad/layers/noise.py
salad/layers/vat.py
salad/models/__init__.py
salad/models/base.py
salad/models/conditionals.py
salad/models/digits.py
salad/models/fan.py
salad/models/gan.py
salad/models/neural.py
salad/models/resnet.py
salad/models/sensorimotor.py
salad/models/transfer.py
salad/models/unet.py
salad/models/utils.py
salad/models/audio/__init__.py
salad/models/digits/__init__.py
salad/models/digits/_legacy.py
salad/models/digits/adv.py
salad/models/digits/assoc.py
salad/models/digits/base.py
salad/models/digits/corr.py
salad/models/digits/dirtt.py
salad/models/digits/ensemble.py
salad/models/vision/__init__.py
salad/models/vision/unet.py
salad/solver/__init__.py
salad/solver/base.py
salad/solver/classification.py
salad/solver/gan.py
salad/solver/openset.py
salad/solver/da/__init__.py
salad/solver/da/advdrop.py
salad/solver/da/advdrop_refactor.py
salad/solver/da/association.py
salad/solver/da/base.py
salad/solver/da/coral.py
salad/solver/da/crossgrad.py
salad/solver/da/dann.py
torch_salad-0.2.1a0.dist-info/METADATA
torch_salad-0.2.1a0.dist-info/RECORD
torch_salad-0.2.1a0.dist-info/WHEEL
torch_salad-0.2.1a0.dist-info/top_level.txt
