Metadata-Version: 2.1
Name: torch-salad
Version: 0.2.1a0
Summary: Semi-supervised Adaptive Learning Across Domains
Home-page: https://domainadaptation.org
Author: Steffen Schneider
Author-email: steffen.schneider@tum.de
License: UNKNOWN
Platform: UNKNOWN
Classifier: Programming Language :: Python :: 3
Classifier: License :: OSI Approved :: Mozilla Public License 2.0 (MPL 2.0)
Classifier: Operating System :: OS Independent
Classifier: Development Status :: 2 - Pre-Alpha
Classifier: Topic :: Scientific/Engineering :: Artificial Intelligence
